{
  "run_ts_utc": "2026-02-17T18:18:28.891764+00:00",
  "traceability": {
    "run_ts_utc": "2026-02-17T18:18:28.891764+00:00",
    "input_parquet": "data\\raw\\sp500_history.parquet",
    "input_candidates": [
      "data\\raw\\sp500_history.parquet",
      "C:\\Users\\dgall\\Downloads\\sp500_history.parquet"
    ],
    "out_canonical": "data\\processed\\sp500_canonical.parquet",
    "out_spy": "data\\raw\\spy_yfinance.parquet",
    "versions": {
      "python": "3.13.5",
      "platform": "Windows-11-10.0.26200-SP0",
      "numpy": "2.1.3",
      "pandas": "2.2.3",
      "pyarrow": "19.0.0",
      "yfinance": "1.1.0"
    },
    "spy_source": "yfinance_download"
  },
  "coverage_summary": {
    "date_min": "1990-01-02",
    "date_max": "2026-01-30",
    "total_rows": 7250110,
    "total_symbols": 1289,
    "symbols_on_last_date": 650,
    "active_symbols": 650,
    "inactive_symbols": 639,
    "sp500_members_min": 498,
    "sp500_members_median": 500.0,
    "sp500_members_max": 507
  },
  "checks": [
    {
      "check": "required_columns_present",
      "passed": true,
      "details": "missing_columns=[]"
    },
    {
      "check": "date_is_datetime",
      "passed": true,
      "details": "date dtype invalido"
    },
    {
      "check": "symbol_is_string",
      "passed": true,
      "details": "symbol dtype invalido"
    },
    {
      "check": "numeric_columns_dtype",
      "passed": true,
      "details": "invalid_numeric_dtype=[]"
    },
    {
      "check": "duplicate_date_symbol",
      "passed": true,
      "details": "duplicate_rows=0"
    },
    {
      "check": "critical_nulls",
      "passed": true,
      "details": "critical_null_count=0"
    },
    {
      "check": "prices_positive",
      "passed": true,
      "details": "invalid_price_rows=0"
    },
    {
      "check": "volume_non_negative",
      "passed": true,
      "details": "invalid_volume_rows=0"
    },
    {
      "check": "ohlc_consistency",
      "passed": true,
      "details": "invalid_ohlc_rows=0"
    },
    {
      "check": "in_sp500_binary",
      "passed": true,
      "details": "invalid_in_sp500_rows=0"
    },
    {
      "check": "spy_required_columns_present",
      "passed": true,
      "details": "spy_missing_columns=[]"
    }
  ]
}